techynotes/__init__.py
techynotes/admin.py
techynotes/apps.py
techynotes/models.py
techynotes/tests.py
techynotes/urls.py
techynotes/views.py
techynotes/static/css/mainscreen.css
techynotes/static/images/clone.gif
techynotes/static/images/login_pg.png
techynotes/static/images/repos_loading.gif
techynotes/static/js/mainscreen.js
techynotes/templates/homepage.html
techynotes-1.0.0.dist-info/METADATA
techynotes-1.0.0.dist-info/WHEEL
techynotes-1.0.0.dist-info/top_level.txt
techynotes-1.0.0.dist-info/RECORD
